pillow_mbm/__init__.py
pillow_mbm/__main__.py
pillow_mbm-0.2.0.dist-info/licenses/LICENSE.md
pillow_mbm-0.2.0.dist-info/METADATA
pillow_mbm-0.2.0.dist-info/WHEEL
pillow_mbm-0.2.0.dist-info/entry_points.txt
pillow_mbm-0.2.0.dist-info/top_level.txt
pillow_mbm-0.2.0.dist-info/RECORD
