Metadata-Version: 2.4
Name: pillow-mbm
Version: 0.2.0
Summary: Kerbal Space Program MBM file conversion plugin
Author-email: Andrew Cassidy <drewcassidy@me.com>
License-Expression: Apache-2.0
Project-URL: Source, https://git.offworldcolonies.nexus/drewcassidy/pillow-mbm
Project-URL: Changelog, https://git.offworldcolonies.nexus/drewcassidy/pillow-mbm/src/branch/main/CHANGELOG.md
Project-URL: Forum Post, https://forum.kerbalspaceprogram.com/index.php?/topic/201606-quicktex-dds-texture-encoderdecoder/&do=findComment&comment=395303
Keywords: pillow,PIL,MBM,Texture,KSP
Classifier: Development Status :: 5 - Production/Stable
Classifier: Intended Audience :: Developers
Classifier: Operating System :: OS Independent
Classifier: Programming Language :: Python :: 3 :: Only
Classifier: Programming Language :: Python :: 3
Classifier: Topic :: Games/Entertainment :: Simulation
Classifier: Topic :: Multimedia :: Graphics
Classifier: Topic :: Multimedia :: Graphics :: Graphics Conversion
Requires-Python: >=3.10
License-File: LICENSE.md
Requires-Dist: Click>=8.0
Requires-Dist: Pillow>=8.0
Dynamic: license-file
